ocs_sample_library_preview/Authentication.py
ocs_sample_library_preview/BaseClient.py
ocs_sample_library_preview/DataViews.py
ocs_sample_library_preview/EDSClient.py
ocs_sample_library_preview/OCSClient.py
ocs_sample_library_preview/SdsError.py
ocs_sample_library_preview/Streams.py
ocs_sample_library_preview/Types.py
ocs_sample_library_preview/__init__.py
ocs_sample_library_preview/DataView/DataItem.py
ocs_sample_library_preview/DataView/DataItemField.py
ocs_sample_library_preview/DataView/DataItems.py
ocs_sample_library_preview/DataView/DataMapping.py
ocs_sample_library_preview/DataView/DataView.py
ocs_sample_library_preview/DataView/DataViewShapes.py
ocs_sample_library_preview/DataView/Field.py
ocs_sample_library_preview/DataView/FieldKind.py
ocs_sample_library_preview/DataView/FieldMapping.py
ocs_sample_library_preview/DataView/FieldSet.py
ocs_sample_library_preview/DataView/FieldSets.py
ocs_sample_library_preview/DataView/FieldSource.py
ocs_sample_library_preview/DataView/Query.py
ocs_sample_library_preview/DataView/__init__.py
ocs_sample_library_preview/SDS/SdsBoundaryType.py
ocs_sample_library_preview/SDS/SdsNamespace.py
ocs_sample_library_preview/SDS/SdsSearchMode.py
ocs_sample_library_preview/SDS/SdsStream.py
ocs_sample_library_preview/SDS/SdsStreamExtrapolation.py
ocs_sample_library_preview/SDS/SdsStreamIndex.py
ocs_sample_library_preview/SDS/SdsStreamMode.py
ocs_sample_library_preview/SDS/SdsStreamPropertyOverride.py
ocs_sample_library_preview/SDS/SdsStreamView.py
ocs_sample_library_preview/SDS/SdsStreamViewMap.py
ocs_sample_library_preview/SDS/SdsStreamViewProperty.py
ocs_sample_library_preview/SDS/SdsType.py
ocs_sample_library_preview/SDS/SdsTypeCode.py
ocs_sample_library_preview/SDS/SdsTypeProperty.py
ocs_sample_library_preview/SDS/__init__.py
ocs_sample_library_hub-0.1.20.dist-info/LICENSE
ocs_sample_library_hub-0.1.20.dist-info/METADATA
ocs_sample_library_hub-0.1.20.dist-info/WHEEL
ocs_sample_library_hub-0.1.20.dist-info/top_level.txt
ocs_sample_library_hub-0.1.20.dist-info/RECORD
