Metadata-Version: 2.1
Name: ocs-sample-library-hub
Version: 0.1.20
Summary: OCS (OSIsoft Cloud Services) client library - patched 0.1.17rc0 api/v1 + /stored
Home-page: https://github.com/cfoisy-osisoft/sample-ocs-sample_libraries-python
Author: OSIsoft
Author-email: cfoisy@osisoft.com
License: Apache 2.0
Platform: UNKNOWN
Classifier: Programming Language :: Python :: 3
Classifier: License :: OSI Approved :: Apache Software License
Classifier: Operating System :: OS Independent
Requires-Python: >=3.6
Requires-Dist: requests (>=2.25.1)
Requires-Dist: python-dateutil (>=2.8.1)
